mopidy_asyncio_client/__init__.py
mopidy_asyncio_client/client.py
mopidy_asyncio_client/messages.py
mopidy_asyncio_client/mopidy_api.py
mopidy_asyncio_client-3.1.0.dist-info/LICENSE
mopidy_asyncio_client-3.1.0.dist-info/METADATA
mopidy_asyncio_client-3.1.0.dist-info/WHEEL
mopidy_asyncio_client-3.1.0.dist-info/top_level.txt
mopidy_asyncio_client-3.1.0.dist-info/RECORD
