Metadata-Version: 2.1
Name: mopidy-asyncio-client
Version: 3.1.0
Summary: Async Mopidy client using JSON/RPC Websocket interface
Home-page: https://codeberg.org/sph/mopidy-asyncio-client
Author: Stephan Helma
Author-email: s.p.helma@gmx.net
License: GNU General Public License, Version 2 or later
Project-URL: Bug Tracker, https://codeberg.org/sph/mopidy-asyncio-client/issues
Platform: UNKNOWN
Classifier: Development Status :: 5 - Production/Stable
Classifier: Environment :: No Input/Output (Daemon)
Classifier: Framework :: AsyncIO
Classifier: Intended Audience :: Developers
Classifier: License :: OSI Approved :: GNU General Public License v2 or later (GPLv2+)
Classifier: Operating System :: OS Independent
Classifier: Programming Language :: Python :: 3
Classifier: Programming Language :: Python :: 3.6
Classifier: Programming Language :: Python :: 3.7
Classifier: Programming Language :: Python :: 3.8
Classifier: Programming Language :: Python :: 3.9
Classifier: Topic :: Multimedia :: Sound/Audio :: Players
Requires-Python: >=3.6
License-File: LICENSE
Requires-Dist: websockets
Requires-Dist: setuptools
Provides-Extra: dev
Requires-Dist: twine ; extra == 'dev'
Requires-Dist: wheel ; extra == 'dev'
Provides-Extra: release
Requires-Dist: twine ; extra == 'release'
Requires-Dist: wheel ; extra == 'release'
